krewlyzer-0.3.2.dist-info/METADATA
krewlyzer-0.3.2.dist-info/WHEEL
krewlyzer-0.3.2.dist-info/entry_points.txt
krewlyzer-0.3.2.dist-info/licenses/LICENSE
krewlyzer.libs/libbz2-a1e77c99.so.1
krewlyzer.libs/libcrypto-bdaed0ea.so.1.1
krewlyzer.libs/libssl-60250281.so.1.1
krewlyzer/__init__.py
krewlyzer/_core.cpython-311-x86_64-linux-gnu.so
krewlyzer/cli.py
krewlyzer/data/.gitkeep
krewlyzer/data/CNVdependency/.Rhistory
krewlyzer/data/CNVdependency/GRCh37.p13_centromere_UCSC-gapTable.txt
krewlyzer/data/CNVdependency/GRCh38.GCA_000001405.2_centromere_acen.txt
krewlyzer/data/CNVdependency/gc_hg19_1000kb.wig
krewlyzer/data/CNVdependency/gc_hg19_10kb.wig
krewlyzer/data/CNVdependency/gc_hg19_500kb.wig
krewlyzer/data/CNVdependency/gc_hg19_50kb.wig
krewlyzer/data/CNVdependency/gc_hg38_1000kb.wig
krewlyzer/data/CNVdependency/gc_hg38_10kb.wig
krewlyzer/data/CNVdependency/gc_hg38_500kb.wig
krewlyzer/data/CNVdependency/gc_hg38_50kb.wig
krewlyzer/data/CNVdependency/map_hg19_1000kb.wig
krewlyzer/data/CNVdependency/map_hg19_10kb.wig
krewlyzer/data/CNVdependency/map_hg19_500kb.wig
krewlyzer/data/CNVdependency/map_hg19_50kb.wig
krewlyzer/data/CNVdependency/map_hg38_1000kb.wig
krewlyzer/data/CNVdependency/map_hg38_10kb.wig
krewlyzer/data/CNVdependency/map_hg38_500kb.wig
krewlyzer/data/CNVdependency/map_hg38_50kb.wig
krewlyzer/data/CNVdependency/seqinfo_hg19_ucsc.rds
krewlyzer/data/CNVdependency/seqinfo_hg38_ucsc.rds
krewlyzer/data/README.md
krewlyzer/data/TranscriptAnno/transcriptAnno-hg19-10kb.tsv
krewlyzer/data/TranscriptAnno/transcriptAnno-hg19-1kb.tsv
krewlyzer/data/TranscriptAnno/transcriptAnno-hg38-10kb.tsv
krewlyzer/data/TranscriptAnno/transcriptAnno-hg38-1kb.tsv
krewlyzer/extract.py
krewlyzer/fsc.py
krewlyzer/fsd.py
krewlyzer/fsr.py
krewlyzer/helpers.py
krewlyzer/logo.svg
krewlyzer/mfsd.py
krewlyzer/motif.py
krewlyzer/ocf.py
krewlyzer/postprocess.py
krewlyzer/uxm.py
krewlyzer/wps.py
krewlyzer/wrapper.py
krewlyzer-0.3.2.dist-info/RECORD
