Metadata-Version: 2.4
Name: krewlyzer
Version: 0.3.2
Requires-Dist: typer>=0.15.0
Requires-Dist: pysam>=0.22.0
Requires-Dist: pandas>=2.2.0
Requires-Dist: numpy>=1.20.0
Requires-Dist: rich>=13.9.0
Requires-Dist: mkdocs>=1.5.0 ; extra == 'docs'
Requires-Dist: mkdocs-material>=9.5.0 ; extra == 'docs'
Requires-Dist: pytest>=7.0.0 ; extra == 'test'
Requires-Dist: pytest-mock>=3.10.0 ; extra == 'test'
Provides-Extra: docs
Provides-Extra: test
License-File: LICENSE
Summary: Feature extraction tools for circulating tumor DNA from GRCh37 aligned BAM files
Home-Page: https://github.com/msk-access/krewlyzer
Author-email: Ronak Shah <shahr2@mskcc.org>
Requires-Python: >=3.8
Project-URL: Homepage, https://github.com/msk-access/krewlyzer
